{"version":1,"resource":"vscode-remote://wsl%2Bubuntu-18.04/home/jinsu_park/catkin_ws/src/calibration_demo/CMakeLists.txt","entries":[{"id":"2rAl.txt","timestamp":1694664834259},{"id":"4RnF.txt","timestamp":1694664928819},{"id":"GFta.txt","timestamp":1694667684877},{"id":"9XmO.txt","timestamp":1694667760997},{"id":"G3Zv.txt","timestamp":1694749607081},{"id":"hRRL.txt","timestamp":1694749657561},{"id":"Hb0i.txt","timestamp":1694750326561},{"id":"YeWL.txt","timestamp":1694750380541},{"id":"RHVQ.txt","timestamp":1694753270219},{"id":"FAH0.txt","timestamp":1694753337709}]}